physapp/__init__.py
physapp/base.py
physapp/csv.py
physapp/curseur.py
physapp/fonctions.py
physapp/markdown.py
physapp/modelisation.py
physapp/utils.py
physapp-0.3.6.dist-info/LICENSE
physapp-0.3.6.dist-info/METADATA
physapp-0.3.6.dist-info/WHEEL
physapp-0.3.6.dist-info/top_level.txt
physapp-0.3.6.dist-info/RECORD
