Metadata-Version: 2.1
Name: physapp
Version: 0.3.6
Summary: Librairie Python pour la physique appliquée
Home-page: https://github.com/david-therincourt/physapp
Author: David THERINCOURT
Author-email: dtherincourt@gmail.com
Classifier: Programming Language :: Python :: 3
Classifier: License :: OSI Approved :: MIT License
Classifier: Operating System :: OS Independent
Requires-Python: >=3.10
License-File: LICENSE
Requires-Dist: numpy >=1.26.0
Requires-Dist: matplotlib >=3.8.0
Requires-Dist: scipy >=1.11.0
